{
  "todos": [
    {
      "title": "Add some unit tests sa    x     asf            12       d",
      "complete": false,
      "id": 3
    },
    {
      "title": "Do all todos",
      "complete": false,
      "id": 8
    },
    {
      "title": "Finish the project",
      "complete": false,
      "id": 10
    },
    {
      "title": "Complete the edititing todo",
      "complete": true,
      "id": 11
    },
    {
      "title": "If clicks outside of the editing Todo, update todo",
      "complete": true,
      "id": 12
    },
    {
      "title": "If todo is edited, cursor not entered in the todo title field",
      "complete": true,
      "id": 13
    },
    {
      "title": "On editing finish, if title of the todo is empty -> delete todo",
      "complete": true,
      "id": 14
    },
    {
      "title": "Test todo",
      "complete": false,
      "id": 15
    }
  ]
}